sugar/__init__.py
sugar/__version__.py
sugar/main.py
sugar/agent/__init__.py
sugar/agent/base.py
sugar/agent/hooks.py
sugar/agent/subagent_manager.py
sugar/agent/tools.py
sugar/billing/__init__.py
sugar/billing/api_keys.py
sugar/billing/tiers.py
sugar/billing/usage.py
sugar/config/__init__.py
sugar/config/issue_responder_config.py
sugar/config/prompt_config.py
sugar/core/__init__.py
sugar/core/loop.py
sugar/discovery/__init__.py
sugar/discovery/code_quality.py
sugar/discovery/error_monitor.py
sugar/discovery/github_watcher.py
sugar/discovery/test_coverage.py
sugar/executor/__init__.py
sugar/executor/agent_sdk_executor.py
sugar/executor/base.py
sugar/executor/claude_wrapper.py
sugar/executor/hooks.py
sugar/executor/structured_request.py
sugar/executor/thinking_display.py
sugar/integrations/__init__.py
sugar/integrations/github.py
sugar/learning/__init__.py
sugar/learning/adaptive_scheduler.py
sugar/learning/feedback_processor.py
sugar/learning/learnings_writer.py
sugar/mcp/__init__.py
sugar/mcp/server.py
sugar/orchestration/__init__.py
sugar/orchestration/agent_router.py
sugar/orchestration/model_router.py
sugar/orchestration/task_orchestrator.py
sugar/profiles/__init__.py
sugar/profiles/base.py
sugar/profiles/default.py
sugar/profiles/issue_responder.py
sugar/quality_gates/__init__.py
sugar/quality_gates/coordinator.py
sugar/quality_gates/criteria_templates.py
sugar/quality_gates/diff_validator.py
sugar/quality_gates/evidence.py
sugar/quality_gates/failure_handler.py
sugar/quality_gates/functional_verifier.py
sugar/quality_gates/preflight_checks.py
sugar/quality_gates/success_criteria.py
sugar/quality_gates/test_validator.py
sugar/quality_gates/truth_enforcer.py
sugar/quality_gates/verification_gate.py
sugar/ralph/__init__.py
sugar/ralph/config.py
sugar/ralph/profile.py
sugar/ralph/signals.py
sugar/ralph/validator.py
sugar/storage/__init__.py
sugar/storage/issue_response_manager.py
sugar/storage/task_type_manager.py
sugar/storage/work_queue.py
sugarai-3.4.4.dist-info/licenses/LICENSE
sugarai-3.4.4.dist-info/METADATA
sugarai-3.4.4.dist-info/WHEEL
sugarai-3.4.4.dist-info/entry_points.txt
sugarai-3.4.4.dist-info/top_level.txt
sugarai-3.4.4.dist-info/RECORD
