Metadata-Version: 2.4
Name: sugarai
Version: 3.4.4
Summary: 🍰 Sugar - The autonomous layer for AI coding agents. Manages task queues, runs 24/7, ships working code.
Author-email: Steven Leggett <contact@roboticforce.io>
License: AGPL-3.0-or-later
Project-URL: Homepage, https://github.com/roboticforce/sugar
Project-URL: Documentation, https://docs.roboticforce.io/sugar
Project-URL: Repository, https://github.com/roboticforce/sugar
Project-URL: Bug Tracker, https://github.com/roboticforce/sugar/issues
Keywords: claude,autonomous,development,ai,automation
Classifier: Development Status :: 4 - Beta
Classifier: Intended Audience :: Developers
Classifier: License :: OSI Approved :: GNU Affero General Public License v3 or later (AGPLv3+)
Classifier: Programming Language :: Python :: 3
Classifier: Programming Language :: Python :: 3.11
Classifier: Programming Language :: Python :: 3.12
Classifier: Programming Language :: Python :: 3.13
Classifier: Topic :: Software Development :: Libraries :: Python Modules
Classifier: Topic :: Software Development :: Quality Assurance
Requires-Python: >=3.11
License-File: LICENSE
Requires-Dist: click>=8.1.0
Requires-Dist: pyyaml>=6.0
Requires-Dist: aiosqlite>=0.19.0
Requires-Dist: sqlalchemy>=2.0.0
Requires-Dist: python-dotenv>=1.0.0
Requires-Dist: asyncio-throttle>=1.0.0
Requires-Dist: setuptools>=45
Requires-Dist: claude-agent-sdk>=0.1.0
Provides-Extra: github
Requires-Dist: PyGithub>=1.59.0; extra == "github"
Provides-Extra: dev
Requires-Dist: pytest>=7.0.0; extra == "dev"
Requires-Dist: pytest-asyncio>=0.21.0; extra == "dev"
Requires-Dist: pytest-cov>=4.0.0; extra == "dev"
Requires-Dist: black>=23.0.0; extra == "dev"
Requires-Dist: flake8>=6.0.0; extra == "dev"
Requires-Dist: flake8-docstrings>=1.7.0; extra == "dev"
Requires-Dist: isort>=5.12.0; extra == "dev"
Requires-Dist: mypy>=1.0.0; extra == "dev"
Requires-Dist: bandit>=1.7.5; extra == "dev"
Requires-Dist: safety>=2.3.0; extra == "dev"
Requires-Dist: pre-commit>=3.0.0; extra == "dev"
Requires-Dist: types-PyYAML>=6.0.0; extra == "dev"
Requires-Dist: types-requests>=2.28.0; extra == "dev"
Requires-Dist: types-setuptools>=69.0.0; extra == "dev"
Provides-Extra: test
Requires-Dist: pytest>=7.0.0; extra == "test"
Requires-Dist: pytest-asyncio>=0.21.0; extra == "test"
Requires-Dist: pytest-cov>=4.0.0; extra == "test"
Provides-Extra: mcp
Requires-Dist: mcp>=1.0.0; extra == "mcp"
Requires-Dist: starlette>=0.27.0; extra == "mcp"
Requires-Dist: uvicorn>=0.22.0; extra == "mcp"
Dynamic: license-file
